collective.printrss-1.0.5-py2.7-nspkg.pth
collective/printrss/__init__.py
collective/printrss/configure.zcml
collective/printrss/content.py
collective/printrss/interfaces.py
collective/printrss/setuphandlers.py
collective/printrss/testing.py
collective/printrss/browser/__init__.py
collective/printrss/browser/configure.zcml
collective/printrss/browser/macros.pt
collective/printrss/browser/view.pt
collective/printrss/browser/overrides/.gitkeep
collective/printrss/browser/static/.gitkeep
collective/printrss/locales/collective.printrss.pot
collective/printrss/locales/update.sh
collective/printrss/locales/en/LC_MESSAGES/collective.printrss.po
collective/printrss/locales/fr/LC_MESSAGES/collective.printrss.po
collective/printrss/profiles/default/browserlayer.xml
collective/printrss/profiles/default/collectiveprintrss_default.txt
collective/printrss/profiles/default/metadata.xml
collective/printrss/profiles/default/types.xml
collective/printrss/profiles/default/types/rss_feed.xml
collective/printrss/tests/__init__.py
collective/printrss/tests/test_robot.py
collective/printrss/tests/test_rss_feed.py
collective/printrss/tests/test_setup.py
collective/printrss/tests/robot/test_example.robot
collective/printrss/tests/robot/test_rss_feed.robot
collective.printrss-1.0.5.dist-info/DESCRIPTION.rst
collective.printrss-1.0.5.dist-info/METADATA
collective.printrss-1.0.5.dist-info/RECORD
collective.printrss-1.0.5.dist-info/WHEEL
collective.printrss-1.0.5.dist-info/entry_points.txt
collective.printrss-1.0.5.dist-info/metadata.json
collective.printrss-1.0.5.dist-info/namespace_packages.txt
collective.printrss-1.0.5.dist-info/top_level.txt
