Metadata-Version: 2.0
Name: collective.printrss
Version: 1.0.5
Summary: Products to print a rss feed from a given URL.
Home-page: https://pypi.python.org/pypi/collective.printrss
Author: boulch
Author-email: christophe.boulanger@imio.be
License: GPL version 2
Keywords: Python Plone
Platform: UNKNOWN
Classifier: Environment :: Web Environment
Classifier: Framework :: Plone
Classifier: Framework :: Plone :: 4.3
Classifier: Programming Language :: Python
Classifier: Programming Language :: Python :: 2.7
Classifier: Operating System :: OS Independent
Classifier: License :: OSI Approved :: GNU General Public License v2 (GPLv2)
Provides-Extra: test
Requires-Dist: plone.app.portlets
Requires-Dist: plone.app.contenttypes
Requires-Dist: plone.api
Requires-Dist: setuptools
Requires-Dist: z3c.jbot
Requires-Dist: plone.app.dexterity
Provides-Extra: test
Requires-Dist: plone.app.testing; extra == 'test'
Requires-Dist: plone.app.contenttypes; extra == 'test'
Requires-Dist: plone.app.robotframework[debug]; extra == 'test'
